utils.py
omar_rq/__init__.py
omar_rq/callbacks.py
omar_rq/compute_input_stats.py
omar_rq/cosineannealingscheduler.py
omar_rq/downstream.py
omar_rq/get_model.py
omar_rq/predict.py
omar_rq/train.py
omar_rq/utils.py
omar_rq/data/__init__.py
omar_rq/data/data_utils.py
omar_rq/data/discotube.py
omar_rq/data/discotube_text_audio.py
omar_rq/modules/__init__.py
omar_rq/modules/classifier.py
omar_rq/modules/codebooks.py
omar_rq/modules/finite_scalar_quantizer.py
omar_rq/modules/maskingmodel.py
omar_rq/modules/simclr.py
omar_rq/nets/__init__.py
omar_rq/nets/common_former.py
omar_rq/nets/conformer.py
omar_rq/nets/cqt.py
omar_rq/nets/encodec.py
omar_rq/nets/melspectrogram.py
omar_rq/nets/mlp.py
omar_rq/nets/net.py
omar_rq/nets/rope.py
omar_rq/nets/transformer.py
omar_rq/nets/waveform.py
omar_rq/prediction/callbacks.py
omar_rq/prediction/dataset.py
omar_rq/probe/data/__init__.py
omar_rq/probe/data/magnatagatune.py
omar_rq/probe/data/nsynth_pitch.py
omar_rq/probe/modules/__init__.py
omar_rq/probe/modules/sequence_classifiers.py
omar_rq-0.2.1.dist-info/licenses/LICENSE
omar_rq-0.2.1.dist-info/METADATA
omar_rq-0.2.1.dist-info/WHEEL
omar_rq-0.2.1.dist-info/top_level.txt
omar_rq-0.2.1.dist-info/RECORD
