Metadata-Version: 2.4
Name: omar-rq
Version: 0.2.1
Summary: Wrapper library to use the OMAR-RQ models for audio music representation
Author-email: Pablo Alonso <pablo.alonso@upf.edu>, Pedro Ramoneda <pedro.ramoneda@upf.edu>, "R. Oguz Araz" <recepoguz.araz@upf.edu>
License: AGPL-3.0 license
Project-URL: Issues, https://https://github.com/MTG/omar-rq/issues/
Project-URL: Homepage, https://github.com/username/omar-rq/
Keywords: deep learning,audio,transformers,mir,music,representation learning,self-supervised learning
Classifier: Intended Audience :: Developers
Classifier: Intended Audience :: Science/Research
Classifier: License :: OSI Approved :: GNU Affero General Public License v3
Classifier: Topic :: Scientific/Engineering :: Artificial Intelligence
Classifier: Topic :: Software Development :: Libraries
Classifier: Topic :: Multimedia :: Sound/Audio :: Analysis
Classifier: Programming Language :: Python :: 3
Classifier: Programming Language :: Python :: 3.10
Classifier: Programming Language :: Python :: 3.11
Classifier: Programming Language :: Python :: 3.12
Classifier: Programming Language :: Python :: 3.13
Requires-Python: >=3.10
License-File: LICENSE
Requires-Dist: lightning<3.0,>=2.3
Requires-Dist: torch<3.0,>=2.6
Requires-Dist: torchaudio<3.0,>=2.6
Requires-Dist: gin-config<1.0,>=0.5
Requires-Dist: einops<1.0,>=0.8
Requires-Dist: transformers<5.0,>=4.50
Provides-Extra: dev
Requires-Dist: ruff~=0.14; extra == "dev"
Requires-Dist: pytest; extra == "dev"
Provides-Extra: train
Requires-Dist: bayesian_optimization~=1.5.1; extra == "train"
Requires-Dist: matplotlib; extra == "train"
Requires-Dist: scikit_learn~=1.5.2; extra == "train"
Requires-Dist: scipy~=1.14.1; extra == "train"
Requires-Dist: wandb; extra == "train"
Dynamic: license-file
